core/utils/__init__.py
core/utils/classes/__init__.py
core/utils/classes/collection/__init__.py
core/utils/classes/collection/collection.py
core/utils/classes/item/__init__.py
core/utils/classes/item/item.py
core/utils/classes/item/items.py
core/utils/classes/store/__init__.py
core/utils/classes/store/store.py
core/utils/collections/__init__.py
core/utils/collections/dict_collection.py
core/utils/exceptions/__init__.py
core/utils/functions/__init__.py
core/utils/functions/datetime.py
core/utils/functions/object.py
core/utils/placeholders/__init__.py
core/utils/py.typed
core_utils-0.2.3.dist-info/LICENSE
core_utils-0.2.3.dist-info/METADATA
core_utils-0.2.3.dist-info/WHEEL
core_utils-0.2.3.dist-info/RECORD
