Metadata-Version: 2.1
Name: core-utils
Version: 0.2.3
Summary: A repository for core Python utilities
License: MIT
Author: Sean O'Leary
Author-email: seamicole@gmail.com
Requires-Python: >=3.10,<4.0
Classifier: License :: OSI Approved :: MIT License
Classifier: Programming Language :: Python :: 3
Classifier: Programming Language :: Python :: 3.10
Classifier: Programming Language :: Python :: 3.11
Requires-Dist: pytz (>=2023.3,<2024.0)
